upload/ImageUpload.py
upload/__init__.py
EasyImageUpload-0.0.9.dist-info/LICENSE
EasyImageUpload-0.0.9.dist-info/METADATA
EasyImageUpload-0.0.9.dist-info/WHEEL
EasyImageUpload-0.0.9.dist-info/top_level.txt
EasyImageUpload-0.0.9.dist-info/RECORD
